skivvy/__init__.py
skivvy/__main__.py
skivvy/custom_matchers.py
skivvy/matchers.py
skivvy/skivvy.py
skivvy/skivvy_config.py
skivvy/util/__init__.py
skivvy/util/dict_util.py
skivvy/util/file_util.py
skivvy/util/http_util.py
skivvy/util/log.py
skivvy/util/scope.py
skivvy/util/str_util.py
skivvy/verify.py
skivvy-0.517.dist-info/WHEEL
skivvy-0.517.dist-info/entry_points.txt
skivvy-0.517.dist-info/METADATA
skivvy-0.517.dist-info/RECORD
