Metadata-Version: 2.3
Name: skivvy
Version: 0.517
Summary: A simple tool for testing JSON/HTTP APIs
Author: Jonas Holmer
Author-email: Jonas Holmer <jonas.holmer@gmail.com>
Classifier: Development Status :: 3 - Alpha
Classifier: Intended Audience :: Developers
Classifier: Topic :: Software Development :: Quality Assurance
Classifier: Topic :: Software Development :: Testing
Classifier: Programming Language :: Python
Requires-Dist: pyopenssl
Requires-Dist: requests
Requires-Dist: docopt-ng
Requires-Python: >=3.13
Project-URL: Homepage, https://github.com/hyrfilm/skivvy
